dbstream/DBStream.py
dbstream/__init__.py
dbstream/tunnel.py
dbstream/tools/__init__.py
dbstream/tools/dck_infos.py
dbstream/tools/parse_data.py
dbstream/tools/print_colors.py
dbstream/tools/regex.py
dbstream-0.1.2.dist-info/LICENSE
dbstream-0.1.2.dist-info/METADATA
dbstream-0.1.2.dist-info/WHEEL
dbstream-0.1.2.dist-info/top_level.txt
dbstream-0.1.2.dist-info/RECORD
