Metadata-Version: 2.1
Name: dbstream
Version: 0.1.2
Summary: A meta package to be connected to several databases
Home-page: https://github.com/dacker-team/dbstream
Author: Dacker
Author-email: hello@dacker.co
License: UNKNOWN
Platform: UNKNOWN
Classifier: Programming Language :: Python :: 3
Classifier: License :: OSI Approved :: MIT License
Classifier: Operating System :: OS Independent
Requires-Python: >=3
Requires-Dist: sshtunnel (==0.1.5)
Requires-Dist: dacktool (>=0.0.7)
